docsvault/__init__.py
docsvault/__main__.py
docsvault/api.py
docsvault/funcs.py
docsvault/settings.py
docsvault/vault.py
docsvault/webui.py
docsvault/wsgi.py
docsvault/static/favicon.ico
docsvault/static/index.html
docsvault/static/css/app.b42043e4.css
docsvault/static/css/chunk-vendors.5699e6ca.css
docsvault/static/img/logo.82b9c7a5.png
docsvault/static/js/app.509b8eb1.js
docsvault/static/js/app.509b8eb1.js.map
docsvault/static/js/chunk-vendors.eecf412e.js
docsvault/static/js/chunk-vendors.eecf412e.js.map
docsvault-0.1.4.dist-info/LICENSE
docsvault-0.1.4.dist-info/METADATA
docsvault-0.1.4.dist-info/WHEEL
docsvault-0.1.4.dist-info/entry_points.txt
docsvault-0.1.4.dist-info/top_level.txt
docsvault-0.1.4.dist-info/RECORD
